odoo/addons/product_category_tax/README.rst
odoo/addons/product_category_tax/__init__.py
odoo/addons/product_category_tax/__manifest__.py
odoo/addons/product_category_tax/i18n/hr.po
odoo/addons/product_category_tax/i18n/product_category_tax.pot
odoo/addons/product_category_tax/models/__init__.py
odoo/addons/product_category_tax/models/product_category.py
odoo/addons/product_category_tax/models/product_product.py
odoo/addons/product_category_tax/models/product_template.py
odoo/addons/product_category_tax/readme/CONFIGURATION.rst
odoo/addons/product_category_tax/readme/CONTRIBUTORS.rst
odoo/addons/product_category_tax/readme/DESCRIPTION.rst
odoo/addons/product_category_tax/readme/USAGE.rst
odoo/addons/product_category_tax/static/description/icon.png
odoo/addons/product_category_tax/static/description/index.html
odoo/addons/product_category_tax/tests/__init__.py
odoo/addons/product_category_tax/tests/test_product_category_tax.py
odoo/addons/product_category_tax/views/product_category.xml
odoo/addons/product_category_tax/views/product_template.xml
odoo14_addon_product_category_tax-14.0.1.1.1.dist-info/METADATA
odoo14_addon_product_category_tax-14.0.1.1.1.dist-info/WHEEL
odoo14_addon_product_category_tax-14.0.1.1.1.dist-info/top_level.txt
odoo14_addon_product_category_tax-14.0.1.1.1.dist-info/RECORD
